setup.py
smla_cut.egg-info/PKG-INFO
smla_cut.egg-info/SOURCES.txt
smla_cut.egg-info/dependency_links.txt
smla_cut.egg-info/top_level.txt
src/__init__.py
src/cut.py